{
  "inGameName": "Tools of the Trade",
  "description": "\"Show me that you know how to use a real, proper tool, Prospector! Use one of our guns to take down some Rattlers.\"",
  "faction": "Korolev",
  "factionReputation": 160,
  "difficulty": "Invalid",
  "failConditions": [],
  "objectives": [
    {
      "type": "Kills",
      "maxProgress": 10,
      "killConditions": {
        "m_killTarget": "EYKillTypeAction::Creatures",
        "m_allowedWeaponCategories": [],
        "m_allowedSpecificWeapons": [
          {
            "DataTable": {
              "ObjectName": "DataTable PRO_Weapons",
              "ObjectPath": "Prospect/Content/DataTables/PRO_Weapons.0"
            },
            "RowName": "WP_A_Pistol_Bullet_01"
          },
          {
            "DataTable": {
              "ObjectName": "DataTable PRO_Weapons",
              "ObjectPath": "Prospect/Content/DataTables/PRO_Weapons.0"
            },
            "RowName": "WP_A_AR_Bullet_01"
          },
          {
            "DataTable": {
              "ObjectName": "DataTable PRO_Weapons",
              "ObjectPath": "Prospect/Content/DataTables/PRO_Weapons.0"
            },
            "RowName": "WP_A_SGun_Energy_01"
          },
          {
            "DataTable": {
              "ObjectName": "DataTable PRO_Weapons",
              "ObjectPath": "Prospect/Content/DataTables/PRO_Weapons.0"
            },
            "RowName": "WP_A_BR_Bullet_01"
          },
          {
            "DataTable": {
              "ObjectName": "DataTable PRO_Weapons",
              "ObjectPath": "Prospect/Content/DataTables/PRO_Weapons.0"
            },
            "RowName": "WP_A_HVY_Shell_01"
          },
          {
            "DataTable": {
              "ObjectName": "DataTable PRO_Weapons",
              "ObjectPath": "Prospect/Content/DataTables/PRO_Weapons.0"
            },
            "RowName": "WP_A_Sniper_Gauss_01"
          },
          {
            "DataTable": {
              "ObjectName": "DataTable PRO_Weapons",
              "ObjectPath": "Prospect/Content/DataTables/PRO_Weapons.0"
            },
            "RowName": "WP_A_Launch_MSL_01"
          },
          {
            "DataTable": {
              "ObjectName": "DataTable PRO_Weapons",
              "ObjectPath": "Prospect/Content/DataTables/PRO_Weapons.0"
            },
            "RowName": "WP_A_SMG_Shard_01"
          },
          {
            "DataTable": {
              "ObjectName": "DataTable PRO_Weapons",
              "ObjectPath": "Prospect/Content/DataTables/PRO_Weapons.0"
            },
            "RowName": "WP_A_Sniper_Gauss_01"
          },
          {
            "DataTable": {
              "ObjectName": "DataTable PRO_Weapons",
              "ObjectPath": "Prospect/Content/DataTables/PRO_Weapons.0"
            },
            "RowName": "WP_A_Launch_MSL_01"
          }
        ],
        "m_specificAIEnemyTypeToKill": "EYEnemyType::Rattler"
      }
    }
  ],
  "rewards": [
    {
      "item": "KorolevScrip",
      "amount": 3,
      "isEndOfChainReward": false,
      "isUnlockReward": false
    },
    {
      "item": "SoftCurrency",
      "amount": 5300,
      "isEndOfChainReward": false,
      "isUnlockReward": false
    }
  ],
  "unlockLevel": 0,
  "unlockContracts": [
    "Inevitable Automation"
  ],
  "isMain": true
}