{
  "inGameName": "Through the Optic Glass",
  "description": "\"A new factory robot malfunctioned and took out another's eyes. It's best we don't advertise the accident, so get us replacement parts from the surface.\"",
  "faction": "Korolev",
  "factionReputation": 130,
  "difficulty": "Invalid",
  "failConditions": [],
  "objectives": [
    {
      "type": "OwnNumOfItem",
      "maxProgress": 7,
      "itemToOwn": "UncommonVelticite"
    },
    {
      "type": "OwnNumOfItem",
      "maxProgress": 5,
      "itemToOwn": "Optic Glass"
    }
  ],
  "rewards": [
    {
      "item": "KM-9 'Scrapper'",
      "amount": 1,
      "isEndOfChainReward": false,
      "isUnlockReward": false
    },
    {
      "item": "KorolevScrip",
      "amount": 2,
      "isEndOfChainReward": false,
      "isUnlockReward": false
    },
    {
      "item": "SoftCurrency",
      "amount": 11000,
      "isEndOfChainReward": false,
      "isUnlockReward": false
    }
  ],
  "unlockLevel": 0,
  "unlockContracts": [
    "Spring Cleaning "
  ],
  "isMain": true
}