{
  "IGN": "Crude Oil Scanning Module",
  "modType": "ScannerUpgrade4",
  "itemWeight": 1,
  "rarity": "Epic",
  "effects": [
    {
      "attribute": "None",
      "type": "Additive",
      "value": 5
    }
  ],
  "compatible": [
    "Tools.Scanner.Scanner4"
  ],
  "sellingFPIncrement": 24,
  "sellingReturnDefault": 10,
  "sellingReturnsPerRarity": {
    "EYItemRarityType::Epic": 2405
  },
  "unlockData": {
    "m_shouldBeDisplayedAsEndOfChainReward": true,
    "m_factionUnlockData": [],
    "m_contractLockPurchase": {
      "DataTable": {
        "ObjectName": "DataTable Contract_DT",
        "ObjectPath": "Prospect/Content/DataTables/Contracts/Contract_DT.0"
      },
      "RowName": "Main-ICA-OilScanModule-2"
    },
    "m_contractLockCrafting": {
      "DataTable": null,
      "RowName": "None"
    }
  },
  "flashlight": false,
  "cost": [
    {
      "shop": "ICA",
      "SoftCurrency": 8000
    }
  ]
}