{
  "inGameName": "Activities_Contract_Hard-ICA-Materials-1",
  "faction": "ICA",
  "factionReputation": 250,
  "difficulty": "Hard",
  "failConditions": [],
  "objectives": [
    {
      "type": "OwnNumOfItem",
      "maxProgress": 8,
      "itemToOwn": "Metallic Alloys"
    }
  ],
  "rewards": [
    {
      "item": "ICAScrip",
      "amount": 30,
      "isEndOfChainReward": false,
      "isUnlockReward": false
    },
    {
      "item": "SoftCurrency",
      "amount": 14000,
      "isEndOfChainReward": false,
      "isUnlockReward": false
    }
  ],
  "unlockLevel": 11,
  "unlockContracts": [],
  "isMain": false
}