{
  "inGameName": "Pale Ivy",
  "description": "We have received reports of strange Ivy-like plants growing on walls and cliffs, bearing rare beautiful blossoms. Needless to say, we need samples.",
  "faction": "Osiris",
  "factionReputation": 18,
  "difficulty": "Easy",
  "failConditions": [],
  "image": "ivy_blossom_job_bg",
  "objectives": [
    {
      "type": "OwnNumOfItem",
      "maxProgress": 5,
      "itemToOwn": "IvyPlant"
    }
  ],
  "rewards": [
    {
      "item": "OsirisScrip",
      "amount": 1,
      "isEndOfChainReward": false,
      "isUnlockReward": false
    },
    {
      "item": "SoftCurrency",
      "amount": 4000,
      "isEndOfChainReward": false,
      "isUnlockReward": false
    },
    {
      "item": "Faction Reputation",
      "amount": 18
    }
  ],
  "unlockLevel": 5,
  "unlockContracts": []
}