{
  "inGameName": "Medium-Brightcaps-Zeal-1",
  "faction": "None",
  "factionReputation": 25,
  "difficulty": "Medium",
  "failConditions": [],
  "objectives": [
    {
      "type": "OwnNumOfItem",
      "maxProgress": 8,
      "itemToOwn": "BrightcapMushroom"
    }
  ],
  "rewards": [
    {
      "item": "KorolevScrip",
      "amount": 1,
      "isEndOfChainReward": false,
      "isUnlockReward": false
    },
    {
      "item": "SoftCurrency",
      "amount": 4400,
      "isEndOfChainReward": false,
      "isUnlockReward": false
    }
  ],
  "unlockLevel": 0,
  "unlockContracts": [],
  "isMain": false
}